LICENSE
MANIFEST.in
README.md
setup.cfg
setup.py
hipnotify/__init__.py
hipnotify/hipnotify.py
hipnotify.egg-info/PKG-INFO
hipnotify.egg-info/SOURCES.txt
hipnotify.egg-info/dependency_links.txt
hipnotify.egg-info/not-zip-safe
hipnotify.egg-info/pbr.json
hipnotify.egg-info/requires.txt
hipnotify.egg-info/top_level.txt
requirements/common.txt
requirements/development.txt
tests/.coverage
tests/__init__.py
tests/conftest.py
tests/test_hipnotify.py
tests/htmlcov/__init__.html
tests/htmlcov/conftest.html
tests/htmlcov/coverage_html.js
tests/htmlcov/index.html
tests/htmlcov/jquery.hotkeys.js
tests/htmlcov/jquery.isonscreen.js
tests/htmlcov/jquery.min.js
tests/htmlcov/jquery.tablesorter.min.js
tests/htmlcov/keybd_closed.png
tests/htmlcov/keybd_open.png
tests/htmlcov/status.dat
tests/htmlcov/style.css
tests/htmlcov/test_hipnotify.html