Metadata-Version: 1.1
Name: hipnotify
Version: 1.0.5
Summary: Deadly simple HipChat API V2 room notification library
Home-page: https://github.com/achiku/hipnotify
Author: Akira Chiku
Author-email: akira.chiku@gmail.com
License: MIT
Keywords: hipnotify
Platform: UNKNOWN
Classifier: Development Status :: 5 - Production/Stable
Classifier: Intended Audience :: Developers
Classifier: License :: OSI Approved :: MIT License
Classifier: Natural Language :: English
Classifier: Programming Language :: Python :: 2
Classifier: Programming Language :: Python :: 2.7
Classifier: Programming Language :: Python :: 3
Classifier: Programming Language :: Python :: 3.3
Classifier: Programming Language :: Python :: 3.4
